{"title": "French farmers wind down fuel blockades after government g", "symbol": "TOTF.PA", "date": "2018-06-13", "time": "11:06 AM"}
{"title": "British automotive company Cosworth eyes New York IPO in 2019", "symbol": "GM.N", "date": "2018-06-07", "time": "8:50 PM"}
{"title": "ECB's Nowotny concerned by Italy but sees no actual crisis -pap", "symbol": "CAGR.PA", "date": "2018-06-12", "time": "7:14 AM"}
{"title": "Steinhoff reports former CEO to South African polic", "symbol": "SNHJ.J", "date": "2018-01-30", "time": "1:15 PM"}
{"title": "UK car output drops for first time since 2009, investment slump", "symbol": "TAMO.NS", "date": "2018-01-31", "time": "12:11 AM"}
{"title": "Asset managers rush to launch MSCI index funds ahead of China A-share inclusion", "symbol": "KBA.P", "date": "2018-01-30", "time": "12:34 AM"}
{"title": "Coffee meets 7UP in Keurig, Dr Pepper Snapple deal", "symbol": "DPS.N", "date": "2018-01-29", "time": "12:44 PM"}
{"title": "Sanofi beats Novo to buy Ablynx for $4.8 billion in biotech M&A boom", "symbol": "SASY.PA", "date": "2018-01-29", "time": "7:59 AM"}
{"title": "Creditors to take 70 percent of Noble Group in $3.5 billion debt restructuring", "symbol": "NOBG.SI", "date": "2018-01-29", "time": "4:54 PM"}
{"title": "BP makes two discoveries in UK North Sea", "symbol": "BP.L", "date": "2018-01-31", "time": "12:08 AM"}
{"title": "Bunge buys U.S. corn flour mills, following ADM takeover approach", "symbol": "BG.N", "date": "2018-01-31", "time": "12:55 AM"}
{"title": "Russia's elite dismiss U.S. list as 'telephone book' of the wealthy", "symbol": "GMKN.MM", "date": "2018-01-30", "time": "6:09 AM"}
{"title": "Amazon, Berkshire, JPMorgan partner to cut U.S. healthcare co", "symbol": "AMZN.O", "date": "2018-01-30", "time": "12:29 PM"}
{"title": "Health investors roll out unwelcome mat for Amazon's arrival", "symbol": "AMZN.O", "date": "2018-01-30", "time": "8:25 PM"}
{"title": "Seaplane that crashed in Sydney killing Compass Group exec was off course - investigato", "symbol": "CPG.L", "date": "2018-01-31", "time": "3:11 AM"}
{"title": "Renault-Nissan group pips VW to become top-selling carmaker in 2017", "symbol": "VOWG_p.DE", "date": "2018-01-30", "time": "6:34 AM"}
{"title": "U.S. washer tariffs put Samsung, LG supply chains through the wring", "symbol": "005380.KS", "date": "2018-01-30", "time": "6:49 AM"}
{"title": "Blackstone bets big on Wall St. information business with Thomson Reuters deal", "symbol": "BX.N", "date": "2018-01-30", "time": "10:06 PM"}
{"title": "Ryanair agrees to recognise British pilots union for first tim", "symbol": "RYA.I", "date": "2018-01-30", "time": "7:42 AM"}
{"title": "Wanda gets lift as Tencent-led group invests $5.4 billion in property uni", "symbol": "0700.HK", "date": "2018-01-30", "time": "7:40 AM"}
{"title": "ArcelorMittal upbeat about 2018, slowly resumes dividend", "symbol": "MT.AS", "date": "2018-01-31", "time": "6:11 AM"}
{"title": "Lender CYBG posts higher first quarter lending, warns mortgage growth to ea", "symbol": "CYBGC.L", "date": "2018-01-30", "time": "7:29 AM"}
{"title": "Britain's Diploma appoints Richard Ingram as CEO", "symbol": "DPLM.L", "date": "2018-01-30", "time": "7:39 AM"}
{"title": "ING quarterly profit misses on costs, weaker financial mark", "symbol": "INGA.AS", "date": "2018-01-31", "time": "7:03 AM"}
{"title": "Domino's sees profit above estimates after 'X Factor' boosts fourth qua", "symbol": "DOM.L", "date": "2018-01-30", "time": "7:37 AM"}
{"title": "Centamin posts fall in 2017 core profit on lower output, higher co", "symbol": "CEY.L", "date": "2018-01-31", "time": "7:28 AM"}
{"title": "Britain's UDG Healthcare expects 18-21 percent growth in full-year profi", "symbol": "UDG.L", "date": "2018-01-30", "time": "7:30 AM"}
{"title": "EnQuest agrees with BP to run decommissioning of Thistle, Deveron", "symbol": "ENQ.L", "date": "2018-01-31", "time": "7:41 AM"}
{"title": "Dairy Crest sales driven by growth across top brand", "symbol": "DCG.L", "date": "2018-01-31", "time": "7:19 AM"}
{"title": "After fifth quarter of losses, Ericsson sees recovery sign", "symbol": "ERICb.ST", "date": "2018-01-31", "time": "6:56 AM"}
{"title": "Defections weaken Dutch banks' fintech defenc", "symbol": "ABNd.AS", "date": "2018-01-31", "time": "8:26 AM"}
{"title": "Order boom helps truck maker Volvo to raise market outlook", "symbol": "VOLVb.ST", "date": "2018-01-31", "time": "6:40 AM"}
{"title": "Britain's SSE raises fiscal year profit outlook, shares up", "symbol": "SSE.L", "date": "2018-01-31", "time": "7:33 AM"}
{"title": "UK's Britvic first quarter revenue up 3.3 percent on demand for carbonated drink", "symbol": "BVIC.L", "date": "2018-01-31", "time": "7:26 AM"}
{"title": "Factbox - A chronology of Thomson Reuters Corp", "symbol": "TRI.TO", "date": "2018-01-31", "time": "5:44 AM"}
{"title": "Finland's Wartsila to take a look at Rolls-Royce's marine business - CEO", "symbol": "WRT1V.HE", "date": "2018-01-31", "time": "8:49 AM"}
{"title": "Fujifilm to take over Xerox, combined into joint ven", "symbol": "4901.T", "date": "2018-01-31", "time": "8:25 AM"}
{"title": "Wizz Air says growth helped by faltering rival", "symbol": "WIZZ.L", "date": "2018-01-31", "time": "7:23 AM"}
{"title": "SAP pushes into sales tracking market with $2.4 billion Callidus buy", "symbol": "SAPG.DE", "date": "2018-01-30", "time": "10:00 AM"}
{"title": "Siemens first quarter profit falls on power and gas declin", "symbol": "SIEGn.DE", "date": "2018-01-31", "time": "6:06 AM"}
{"title": "Telecom Italia proposes separating network - sourc", "symbol": "TLIT.MI", "date": "2018-01-30", "time": "8:59 AM"}
{"title": "U.S. charges take shine off Brazil-driven Santander profi", "symbol": "SAN.MC", "date": "2018-01-31", "time": "10:01 AM"}
{"title": "Xerox reports fourth-quarter lo", "symbol": "XRX.N", "date": "2018-01-31", "time": "8:51 AM"}
{"title": "Germany plans temporary nationalisation of truck toll company", "symbol": "DAIGn.DE", "date": "2018-01-29", "time": "7:22 PM"}
{"title": "HSBC names Charlie Nunn as head of retail bank", "symbol": "HSBA.L", "date": "2018-01-31", "time": "11:30 AM"}
{"title": "Russia's Gazprom buoyant over its position in Europ", "symbol": "GAZP.MM", "date": "2018-01-30", "time": "12:12 PM"}
{"title": "Morgan Stanley to decide on Brexit staff moves early this yea", "symbol": "MS.N", "date": "2018-01-31", "time": "10:36 AM"}
{"title": "China's HNA targets $16 billion in asset sales in first half: Bloomberg", "symbol": "HLT.N", "date": "2018-01-31", "time": "8:21 AM"}
{"title": "SAP forces the pace on cloud, buys $2.4 billion U.S. software firm", "symbol": "SAPG.DE", "date": "2018-01-30", "time": "7:24 AM"}
{"title": "Finnair board member quits after government lambasts CEO pension", "symbol": "FIA1S.HE", "date": "2018-01-31", "time": "11:42 AM"}
{"title": "Central banks have considered issuing cryptocurrencies - Italy economy mini", "symbol": "ENEI.MI", "date": "2018-01-31", "time": "11:01 AM"}
{"title": "SAP CEO targets margins, bullish on world economy", "symbol": "SAPG.DE", "date": "2018-01-30", "time": "8:44 AM"}
{"title": "EU sets import duties on cast iron products from China", "symbol": "SGOB.PA", "date": "2018-01-30", "time": "10:56 AM"}
{"title": "Saudi Aramco considering expansion to India - Nikkei", "symbol": "IPO-ARMO.SE", "date": "2018-01-30", "time": "11:05 AM"}
{"title": "Switch steers Nintendo to best third quarter in eight years, higher outlook", "symbol": "7974.T", "date": "2018-01-31", "time": "7:26 AM"}
{"title": "LPC-Barclays aims to increase presence in middle market deb", "symbol": "BARC.L", "date": "2018-01-30", "time": "11:32 AM"}
{"title": "Noble's creditors in driver's seat as group seeks to slash deb", "symbol": "NOBG.SI", "date": "2018-01-30", "time": "1:17 AM"}
{"title": "China's HNA may face $2.4 billion cash shortfall in first quarter - sourc", "symbol": "BX.N", "date": "2018-01-30", "time": "5:35 AM"}
{"title": "Informa expects \u00a360 million in annual cost savings from UBM deal", "symbol": "INF.L", "date": "2018-01-30", "time": "7:15 AM"}
{"title": "Swatch's Hayek targets high-single-digit growth for 2018", "symbol": "UHR.S", "date": "2018-01-30", "time": "11:40 AM"}
{"title": "In Waymo trial, what fired Uber executive may not say could be key", "symbol": "GOOGL.O", "date": "2018-01-31", "time": "12:21 PM"}
{"title": "Global funds cut stocks, fear inflation could puncture complacency - Reuters poll", "symbol": ".STOXX50E", "date": "2018-01-31", "time": "12:25 PM"}
{"title": "German minister sees diesel tests on animals, humans as irresponsibl", "symbol": "VOWG_p.DE", "date": "2018-01-30", "time": "11:43 AM"}
{"title": "Siemens Gamesa posts strong new orders as key markets recov", "symbol": "SGREN.MC", "date": "2018-01-30", "time": "11:55 AM"}
{"title": "China's Li says ties with Britain to stay unchanged through Brexi", "symbol": "EDF.PA", "date": "2018-01-31", "time": "12:26 AM"}
{"title": "Amid angst over iPhone X, Wall Street braces for weak forecast from Appl", "symbol": "AAPL.O", "date": "2018-01-30", "time": "12:09 PM"}
{"title": "Health insurer Aetna quarterly profit soars 75.5 percen", "symbol": "AET.N", "date": "2018-01-30", "time": "11:44 AM"}
{"title": "Stuttgart prosecutor investigates Bosch over Chrysler emissions rol", "symbol": "FCHA.MI", "date": "2018-01-31", "time": "10:57 AM"}
{"title": "Swiss sensor maker Sensirion gears up for flotation - sourc", "symbol": "JPM.N", "date": "2018-01-30", "time": "12:00 PM"}
{"title": "Nordic countries oppose EU plans for digital tax on firms' turnov", "symbol": "FB.O", "date": "2018-05-31", "time": "10:05 PM"}
{"title": "Airline executives brace for oil price turbulence at Sydney gathering", "symbol": "QAN.AX", "date": "2018-05-31", "time": "11:04 PM"}
{"title": "Icahn sells 10.5 million Herbalife shares back to company", "symbol": "HLF.N", "date": "2018-05-31", "time": "8:01 PM"}
{"title": "SoftBank joins GM in self-driving car race; GM shares soa", "symbol": "9984.T", "date": "2018-05-31", "time": "11:38 AM"}
{"title": "Facebook used less for news as youngsters turn to WhatsApp - Reuters Insti", "symbol": "FB.O", "date": "2018-06-13", "time": "11:03 PM"}
{"title": "Struggling UK restaurants could make billions by switching opening hours - study", "symbol": "JE.L", "date": "2018-06-13", "time": "11:10 PM"}
{"title": "Airbus A321LR long-range jet completes maiden fligh", "symbol": "AIR.PA", "date": "2018-01-31", "time": "11:30 AM"}
{"title": "VW suspends chief lobbyist over diesel fum", "symbol": "VOWG_p.DE", "date": "2018-01-30", "time": "12:19 PM"}
{"title": "Israel's Blockchain Mining looks at Nasdaq, Toronto listing", "symbol": "BLCM.TA", "date": "2018-01-30", "time": "12:24 PM"}
{"title": "Boeing workers vote for 'micro-union' at South Carolina plan", "symbol": "BA.N", "date": "2018-05-31", "time": "11:05 AM"}
{"title": "New Zealand push on clean power comes with high political, economic risk", "symbol": "GNE.NZ", "date": "2018-06-01", "time": "1:26 AM"}
{"title": "Exclusive - Venezuela eyes first-ever refining of foreign oil: documen", "symbol": "COP.N", "date": "2018-06-13", "time": "9:27 PM"}
{"title": "Mexico judge cancels arrest warrant for JPMorgan executive, bank say", "symbol": "JPM.N", "date": "2018-06-13", "time": "11:47 PM"}
{"title": "Comcast offers $65 billion to lure Fox from Disney bid", "symbol": "CMCSA.O", "date": "2018-06-13", "time": "8:09 PM"}
{"title": "Unilever bolsters ice cream business with Romania's Betty Ic", "symbol": "ULVR.L", "date": "2018-01-31", "time": "1:36 PM"}
{"title": "Volkswagen suspends chief lobbyist over diesel fum", "symbol": "VOWG_p.DE", "date": "2018-01-30", "time": "12:31 PM"}
{"title": "Australia's Atlas Iron says has been told does not have rights to some shipping berth", "symbol": "AGO.AX", "date": "2018-06-14", "time": "1:04 AM"}
{"title": "Apple to undercut popular law-enforcement tool for cracking iPhon", "symbol": "AAPL.O", "date": "2018-06-13", "time": "8:15 PM"}
{"title": "U.S. labor costs increase solidly in the fourth qua", "symbol": "SBUX.O", "date": "2018-01-31", "time": "1:42 PM"}
{"title": "UK government does not see Capita heading same way as Carillion - PM's spokesman", "symbol": "CPI.L", "date": "2018-01-31", "time": "1:41 PM"}
{"title": "Samsonite's shares set to rise 7.8 percent as CEO steps down", "symbol": "1910.HK", "date": "2018-06-01", "time": "1:31 AM"}
{"title": "Samsonite's shares set to rise 7.8 percent as CEO steps down", "symbol": "1910.HK", "date": "2018-06-01", "time": "1:30 AM"}
{"title": "Citigroup denies criminal cartel allegations expected in Australia", "symbol": "C.N", "date": "2018-06-01", "time": "1:58 AM"}
{"title": "Australian regulator says 'extensive' investigation behind looming charges against ANZ, Deutsch", "symbol": "DBKGn.DE", "date": "2018-06-01", "time": "2:06 AM"}
{"title": "Deutsche Bank says it will defend itself against cartel charges in Australia", "symbol": "DBKGn.DE", "date": "2018-06-01", "time": "2:06 AM"}
{"title": "China property sales pick up as developers push projects to mark", "symbol": "2007.HK", "date": "2018-06-14", "time": "3:11 AM"}
{"title": "UK funds raise stocks to 2-1/2-year high, cash at five-year low", "symbol": ".SPX", "date": "2018-01-31", "time": "12:17 PM"}
{"title": "French trade unions voice opposition to Alstom/Siemens tie-up deal", "symbol": "ALSO.PA", "date": "2018-01-30", "time": "1:45 PM"}
{"title": "Walmart to share inventory data with suppliers in battle with Amazon", "symbol": "WMT.N", "date": "2018-01-30", "time": "1:20 PM"}
{"title": "Spending pinch, royal wedding give UK shops worst May in 12 years - BDO", "symbol": "AMZN.O", "date": "2018-06-07", "time": "11:07 PM"}
{"title": "BP complains to Canada regulator about Enbridge oil pipeline action", "symbol": "BP.L", "date": "2018-06-07", "time": "9:54 PM"}
{"title": "Walmart sues to bar former tax executive from joining Amazon", "symbol": "WMT.N", "date": "2018-06-07", "time": "5:05 PM"}
{"title": "Australia's Tabcorp in talks to exit underperforming Sun B", "symbol": "TAH.AX", "date": "2018-06-07", "time": "11:43 PM"}
{"title": "Musk's Boring Company wins bid to build high-speed system in Chicago", "symbol": "TSLA.O", "date": "2018-06-14", "time": "4:34 AM"}
{"title": "U.S. energy firms chasing oil price rally stumble on old baggag", "symbol": "DVN.N", "date": "2018-06-14", "time": "5:24 AM"}
{"title": "Wall Street wants more female traders, but old perceptions die hard", "symbol": "BARC.L", "date": "2018-06-14", "time": "5:04 AM"}
{"title": "Qantas and Air NZ sign alliance as downunder tourism boom", "symbol": "QAN.AX", "date": "2018-06-01", "time": "2:11 AM"}
{"title": "Renault's Ghosn likely to step down as CEO before term ends - FT", "symbol": "RENA.PA", "date": "2018-06-14", "time": "5:43 AM"}
{"title": "Airbus 'not paralyzed' by wait for new CEO: planemaking chief", "symbol": "AIR.PA", "date": "2018-06-01", "time": "4:11 AM"}
{"title": "Airbus not paralysed by wait for new CEO - planemaking chief", "symbol": "AIR.PA", "date": "2018-06-01", "time": "4:26 AM"}
{"title": "Second jobs, once rare in Japan, are reshaping attitudes about work", "symbol": "4527.T", "date": "2018-06-08", "time": "12:14 AM"}
{"title": "New Airbus chief says challenging to meet delivery goals -staff memo", "symbol": "UTX.N", "date": "2018-06-01", "time": "2:41 AM"}
{"title": "Luxembourg's Anatol says it will not bid for Slovenia's Cinkarna", "symbol": "CICJ.LJ", "date": "2018-06-14", "time": "5:51 AM"}
{"title": "BRIEF-LRW To Buy Popolare di Vicenza's Nem SG", "symbol": "IPO-BPVS.MI", "date": "2018-01-31", "time": "2:17 PM"}
{"title": "Capita shares plunge 40 percent as UK outsourcer cuts foreca", "symbol": "CPI.L", "date": "2018-01-31", "time": "7:25 AM"}
{"title": "Japan stocks to rise in 2018, but restrained by trade worries - Reuters poll", "symbol": ".N225", "date": "2018-06-01", "time": "4:55 AM"}
{"title": "Google's 'Reserve' tool winning converts, taking search to next level", "symbol": "GOOGL.O", "date": "2018-06-01", "time": "5:09 AM"}
{"title": "California utilities regulator tells SJW to seek merger approval", "symbol": "SJW.N", "date": "2018-06-11", "time": "11:26 PM"}
{"title": "Anglo American agrees to Mitsubishi increasing its stake in copper projec", "symbol": "AAL.L", "date": "2018-06-14", "time": "6:29 AM"}
{"title": "Norwegian wealth fund backed Sorrell's farewell pay at WPP AGM", "symbol": "WPP.L", "date": "2018-06-14", "time": "6:31 AM"}
{"title": "Majestic Wine posts full-year sales growth; cautions on challenging UK mark", "symbol": "WINEW.L", "date": "2018-06-14", "time": "6:37 AM"}
{"title": "China pushes state banks into home rental market at their own risk", "symbol": "0939.HK", "date": "2018-06-04", "time": "11:05 PM"}
{"title": "UK consumers hit the shops after early 2018 freeze - survey", "symbol": "BARC.L", "date": "2018-06-04", "time": "11:06 PM"}
{"title": "Washington state sues Facebook, Google over election ad disclo", "symbol": "FB.O", "date": "2018-06-04", "time": "10:55 PM"}
{"title": "Deeper Brazil government meddling looms over new Petrobras CEO", "symbol": "PETR4.SA", "date": "2018-06-04", "time": "11:36 PM"}
{"title": "British taxpayer set to lose billions in $3.5 billion RBS sal", "symbol": "RBS.L", "date": "2018-06-04", "time": "4:25 PM"}
{"title": "Apple issues new App Store rules aimed at streaming PC-based gam", "symbol": "AAPL.O", "date": "2018-06-05", "time": "12:05 AM"}
{"title": "Anthem CEO stands by plan to move pharmacy management inside in", "symbol": "ANTM.N", "date": "2018-01-31", "time": "2:32 PM"}
{"title": "Global solar forecasts lowered as China cuts support polici", "symbol": "CSIQ.O", "date": "2018-06-06", "time": "11:13 PM"}
{"title": "Nikkei drops as hawkish Fed and trade concerns curb risk appeti", "symbol": ".N225", "date": "2018-06-14", "time": "2:35 AM"}
{"title": "Toshiba completes $18 billion sale of chip unit to Bain consortium", "symbol": "6502.T", "date": "2018-06-01", "time": "5:41 AM"}
{"title": "India's ICICI Bank says CEO Kochhar on planned leav", "symbol": "ICBK.NS", "date": "2018-06-01", "time": "5:46 AM"}
{"title": "Broadcom lays off 1,100 employees after Brocade merg", "symbol": "AVGO.O", "date": "2018-06-14", "time": "9:56 PM"}
{"title": "China Resources Cement plans $534 million share sale for business developmen", "symbol": "1313.HK", "date": "2018-06-12", "time": "1:01 AM"}
{"title": "Venezuela's PDVSA transfers oil at sea despite customer qualm", "symbol": "TASCO.BK", "date": "2018-06-07", "time": "9:50 PM"}
